zsdk/__init__.py
zsdk/api.py
zsdk/logger.py
zsdk/utilities.py
zsdk/zdx/__init__.py
zsdk/zia/__init__.py
zsdk/zia/admin_audit_logs.py
zsdk/zia/admin_roles.py
zsdk/zia/admin_users.py
zsdk/zia/app_total.py
zsdk/zia/data_loss_prevention.py
zsdk/zia/device_groups.py
zsdk/zia/event_logs.py
zsdk/zia/firewall_policies.py
zsdk/zia/intermediate_ca_certs.py
zsdk/zia/locations.py
zsdk/zia/rule_labels.py
zsdk/zia/sandbox_report.py
zsdk/zia/sandbox_settings.py
zsdk/zia/sandbox_submission.py
zsdk/zia/security_policy_settings.py
zsdk/zia/traffic_forwarding.py
zsdk/zia/url_categories.py
zsdk/zia/url_filtering_rules.py
zsdk/zia/user_authentication_settings.py
zsdk/zia/user_management.py
zsdk/zpa/__init__.py
zsdk-1.1.3.1.dist-info/LICENSE
zsdk-1.1.3.1.dist-info/METADATA
zsdk-1.1.3.1.dist-info/WHEEL
zsdk-1.1.3.1.dist-info/RECORD
