Metadata-Version: 2.1
Name: zsdk
Version: 1.1.3.1
Summary: Unofficial Python SDK for Zscaler public API endpoints.
Author: Ryan Ulrick
Author-email: rulrick@zscaler.com
Requires-Python: >=3.9
Classifier: Programming Language :: Python :: 3
Classifier: Programming Language :: Python :: 3.9
Classifier: Programming Language :: Python :: 3.10
Classifier: Programming Language :: Python :: 3.11
Requires-Dist: requests (>=2.31.0,<3.0.0)
Requires-Dist: urllib3 (>=2.0.4,<3.0.0)
